sphinxcontrib_imagesvg-0.1-py3.4-nspkg.pth
sphinxcontrib/imagesvg.py
sphinxcontrib_imagesvg-0.1.dist-info/WHEEL
sphinxcontrib_imagesvg-0.1.dist-info/metadata.json
sphinxcontrib_imagesvg-0.1.dist-info/top_level.txt
sphinxcontrib_imagesvg-0.1.dist-info/RECORD
sphinxcontrib_imagesvg-0.1.dist-info/METADATA
sphinxcontrib_imagesvg-0.1.dist-info/DESCRIPTION.rst
sphinxcontrib_imagesvg-0.1.dist-info/namespace_packages.txt
